ALU.v
module ALU
  #(
    parameter N_BITS  = 6,
    parameter N_LEDS  = 6
    )
   (
    output wire [N_LEDS - 1 : 0] o_led   ,
    input wire  [N_BITS  - 1 : 0] i_A     ,
    input wire  [N_BITS  - 1 : 0] i_B     ,
    input wire  [N_BITS  - 1 : 0] i_OP    ,
    input wire                  reset   ,
    input wire                  clock
    );

    localparam ADD  = 6'b100000;
    localparam SUB  = 6'b100010;
    localparam AND  = 6'b100100;
    localparam OR   = 6'b100101;
    localparam XOR  = 6'b100110;
    localparam SRA  = 6'b000011;
    localparam SRL  = 6'b000010;
    localparam NOR  = 6'b100111;
    
    
    //Vars
    reg [N_BITS - 1 : 0] A = i_A;
    reg [N_BITS - 1 : 0] B = i_B;
    reg [N_BITS - 1 : 0] OP = i_OP;
    reg [N_BITS - 1 : 0] RESULT = 0; 
    
    //initial begin        
    //A = i_A;
    //B = i_B;
    //OP = i_OP;
    //RESULT = 0;
    //end

    always @(posedge clock) begin
        case(OP)
        ADD:begin
                RESULT <= A + B;
            end
        SUB:begin
                RESULT <= A - B;
            end
        AND:begin
                RESULT <= A & B;
            end
        OR:begin
                RESULT <= A | B;
            end
        XOR:begin
                RESULT <= A ^ B;
            end
        SRA:begin
                RESULT <= A >> B;
            end
        SRL:begin
                RESULT <= A << B;
            end
        NOR:begin
                RESULT <= ~(A | B);
            end
            endcase          
    end


assign o_led = RESULT;

endmodule //ALU

tb_ALU.v
module tb_ALU;
  reg [5 : 0] A;
  reg [5 : 0] B;
  reg [5 : 0] OP;
  reg reset;
  reg clock;
  wire [5 : 0] LEDs;
  reg [5 : 0] RESULT;

  
  initial begin
    $dumpfile("dump.vcd"); $dumpvars;
    clock = 0;
    reset = 0;
    
    A = 0;
    B = 0;
    OP = 0;
    
    #10
    A = 2;
    B = 3;
    OP = 6'b100000; //ADD
    
    #10
    A = 6;
    B = 5;
    OP = 6'b100010; //SUB
    
    #10
    A = 5;
    B = 5;
    OP = 6'b100100; //AND

    #10
    A = 5;
    B = 2;
    OP = 6'b100101; //OR
    
    #10
    A = 0;
    B = 0;
    OP = 0;
    
    #10
    A = 0;
    B = 0;
    OP = 0;

  end
  
  always #1 clock = ~clock;
   
  ALU instance_ALU(
        .o_led(LEDs), 
        .i_A (A), 
        .i_B (B), 
        .i_OP(OP),
        .reset(reset),
        .clock(clock)
  );
  
   endmodule

TP1_ALU/TP1_ALU.sim/sim_1/behav/xsim/dump.vcd
$date
   Sat Sep 11 16:53:45 2021
$end
$version
  2020.2
$end
$timescale
  1ps
$end
$scope module tb_ALU $end
$var reg 6 ! A [5:0] $end
$var reg 6 " B [5:0] $end
$var reg 6 # OP [5:0] $end
$var reg 1 $ reset $end
$var reg 1 % clock $end
$var wire 6 & LEDs [5:0] $end
$var reg 6 ' RESULT [5:0] $end
$scope module instance_ALU $end
$var wire 6 & o_led [5:0] $end
$var wire 6 ( i_A [5:0] $end
$var wire 6 ) i_B [5:0] $end
$var wire 6 * i_OP [5:0] $end
$var wire 1 + reset $end
$var wire 1 , clock $end
$var reg 6 - A [5:0] $end
$var reg 6 . B [5:0] $end
$var reg 6 / OP [5:0] $end
$var reg 6 0 RESULT [5:0] $end
$upscope $end
$upscope $end
$enddefinitions $end
#0
$dumpvars
b0 !
b0 "
b0 #
0$
0%
bx &
bx '
b0 (
b0 )
b0 *
0+
0,
bx -
bx .
bx /
bx 0
$end
#1000
1%
b0 &
1,
b0 0
#2000
0%
0,
#3000
1%
1,
b0 0
#4000
0%
0,
#5000
1%
1,
b0 0
#6000
0%
0,
#7000
1%
1,
b0 0
#8000
0%
0,
#9000
1%
1,
b0 0
#10000
b10 !
b11 "
b100000 #
0%
b10 (
b11 )
b100000 *
0,
#11000
1%
bx &
1,
bx 0
#12000
0%
0,
#13000
1%
bx &
1,
bx 0
#14000
0%
0,
#15000
1%
bx &
1,
bx 0
#16000
0%
0,
#17000
1%
bx &
1,
bx 0
#18000
0%
0,
#19000
1%
bx &
1,
bx 0
#20000
b110 !
b101 "
b100010 #
0%
b110 (
b101 )
b100010 *
0,
#21000
1%
bx &
1,
bx 0
#22000
0%
0,
#23000
1%
bx &
1,
bx 0
#24000
0%
0,
#25000
1%
bx &
1,
bx 0
#26000
0%
0,
#27000
1%
bx &
1,
bx 0
#28000
0%
0,
#29000
1%
bx &
1,
bx 0
#30000
b101 !
b101 "
b100100 #
0%
b101 (
b100100 *
0,
#31000
1%
bx &
1,
bx 0
#32000
0%
0,
#33000
1%
bx &
1,
bx 0
#34000
0%
0,
#35000
1%
bx &
1,
bx 0
#36000
0%
0,
#37000
1%
bx &
1,
bx 0
#38000
0%
0,
#39000
1%
bx &
1,
bx 0
#40000
b101 !
b10 "
b100101 #
0%
b10 )
b100101 *
0,
#41000
1%
bx &
1,
bx 0
#42000
0%
0,
#43000
1%
bx &
1,
bx 0
#44000
0%
0,
#45000
1%
bx &
1,
bx 0
#46000
0%
0,
#47000
1%
bx &
1,
bx 0
#48000
0%
0,
#49000
1%
bx &
1,
bx 0
#50000
b0 !
b0 "
b0 #
0%
b0 (
b0 )
b0 *
0,
#51000
1%
b0 &
1,
b0 0
#52000
0%
0,
#53000
1%
1,
b0 0
#54000
0%
0,
#55000
1%
1,
b0 0
#56000
0%
0,
#57000
1%
1,
b0 0
#58000
0%
0,
#59000
1%
1,
b0 0
#60000
b0 !
b0 "
b0 #
0%
0,
#61000
1%
1,
b0 0
#62000
0%
0,
#63000
1%
1,
b0 0
#64000
0%
0,
#65000
1%
1,
b0 0
#66000
0%
0,
#67000
1%
1,
b0 0
#68000
0%
0,
#69000
1%
1,
b0 0
#70000
0%
0,
#71000
1%
1,
b0 0
#72000
0%
0,
#73000
1%
1,
b0 0
#74000
0%
0,
#75000
1%
1,
b0 0
#76000
0%
0,
#77000
1%
1,
b0 0
#78000
0%
0,
#79000
1%
1,
b0 0
#80000
0%
0,
#81000
1%
1,
b0 0
#82000
0%
0,
#83000
1%
1,
b0 0
#84000
0%
0,
#85000
1%
1,
b0 0
#86000
0%
0,
#87000
1%
1,
b0 0
#88000
0%
0,
#89000
1%
1,
b0 0
#90000
0%
0,
#91000
1%
1,
b0 0
#92000
0%
0,
#93000
1%
1,
b0 0
#94000
0%
0,
#95000
1%
1,
b0 0
#96000
0%
0,
#97000
1%
1,
b0 0
#98000
0%
0,
#99000
1%
1,
b0 0
#100000
0%
0,
#101000
1%
1,
b0 0
#102000
0%
0,
#103000
1%
1,
b0 0
#104000
0%
0,
#105000
1%
1,
b0 0
#106000
0%
0,
#107000
1%
1,
b0 0
#108000
0%
0,
#109000
1%
1,
b0 0
#110000
0%
0,
#111000
1%
1,
b0 0
#112000
0%
0,
#113000
1%
1,
b0 0
#114000
0%
0,
#115000
1%
1,
b0 0
#116000
0%
0,
#117000
1%
1,
b0 0
#118000
0%
0,
#119000
1%
1,
b0 0
#120000
0%
0,
#121000
1%
1,
b0 0
#122000
0%
0,
#123000
1%
1,
b0 0
#124000
0%
0,
#125000
1%
1,
b0 0
#126000
0%
0,
#127000
1%
1,
b0 0
#128000
0%
0,
#129000
1%
1,
b0 0
#130000
0%
0,
#131000
1%
1,
b0 0
#132000
0%
0,
#133000
1%
1,
b0 0
#134000
0%
0,
#135000
1%
1,
b0 0
#136000
0%
0,
#137000
1%
1,
b0 0
#138000
0%
0,
#139000
1%
1,
b0 0
#140000
0%
0,
#141000
1%
1,
b0 0
#142000
0%
0,
#143000
1%
1,
b0 0
#144000
0%
0,
#145000
1%
1,
b0 0
#146000
0%
0,
#147000
1%
1,
b0 0
#148000
0%
0,
#149000
1%
1,
b0 0
#150000
0%
0,
#151000
1%
1,
b0 0
#152000
0%
0,
#153000
1%
1,
b0 0
#154000
0%
0,
#155000
1%
1,
b0 0
#156000
0%
0,
#157000
1%
1,
b0 0
#158000
0%
0,
#159000
1%
1,
b0 0
#160000
0%
0,
#161000
1%
1,
b0 0
#162000
0%
0,
#163000
1%
1,
b0 0
#164000
0%
0,
#165000
1%
1,
b0 0
#166000
0%
0,
#167000
1%
1,
b0 0
#168000
0%
0,
#169000
1%
1,
b0 0
#170000
0%
0,
#171000
1%
1,
b0 0
#172000
0%
0,
#173000
1%
1,
b0 0
#174000
0%
0,
#175000
1%
1,
b0 0
#176000
0%
0,
#177000
1%
1,
b0 0
#178000
0%
0,
#179000
1%
1,
b0 0
#180000
0%
0,
#181000
1%
1,
b0 0
#182000
0%
0,
#183000
1%
1,
b0 0
#184000
0%
0,
#185000
1%
1,
b0 0
#186000
0%
0,
#187000
1%
1,
b0 0
#188000
0%
0,
#189000
1%
1,
b0 0
#190000
0%
0,
#191000
1%
1,
b0 0
#192000
0%
0,
#193000
1%
1,
b0 0
#194000
0%
0,
#195000
1%
1,
b0 0
#196000
0%
0,
#197000
1%
1,
b0 0
#198000
0%
0,
#199000
1%
1,
b0 0
#200000
0%
0,
#201000
1%
1,
b0 0
#202000
0%
0,
#203000
1%
1,
b0 0
#204000
0%
0,
#205000
1%
1,
b0 0
#206000
0%
0,
#207000
1%
1,
b0 0
#208000
0%
0,
#209000
1%
1,
b0 0
#210000
0%
0,
#211000
1%
1,
b0 0
#212000
0%
0,
#213000
1%
1,
b0 0
#214000
0%
0,
#215000
1%
1,
b0 0
#216000
0%
0,
#217000
1%
1,
b0 0
#218000
0%
0,
#219000
1%
1,
b0 0
#220000
0%
0,
#221000
1%
1,
b0 0
#222000
0%
0,
#223000
1%
1,
b0 0
#224000
0%
0,
#225000
1%
1,
b0 0
#226000
0%
0,
#227000
1%
1,
b0 0
#228000
0%
0,
#229000
1%
1,
b0 0
#230000
0%
0,
#231000
1%
1,
b0 0
#232000
0%
0,
#233000
1%
1,
b0 0
#234000
0%
0,
#235000
1%
1,
b0 0
#236000
0%
0,
#237000
1%
1,
b0 0
#238000
0%
0,
#239000
1%
1,
b0 0
#240000
0%
0,
#241000
1%
1,
b0 0
#242000
0%
0,
#243000
1%
1,
b0 0
#244000
0%
0,
#245000
1%
1,
b0 0
#246000
0%
0,
#247000
1%
1,
b0 0
#248000
0%
0,
#249000
1%
1,
b0 0
#250000
0%
0,
#251000
1%
1,
b0 0
#252000
0%
0,
#253000
1%
1,
b0 0
#254000
0%
0,
#255000
1%
1,
b0 0
#256000
0%
0,
#257000
1%
1,
b0 0
#258000
0%
0,
#259000
1%
1,
b0 0
#260000
0%
0,
#261000
1%
1,
b0 0
#262000
0%
0,
#263000
1%
1,
b0 0
#264000
0%
0,
#265000
1%
1,
b0 0
#266000
0%
0,
#267000
1%
1,
b0 0
#268000
0%
0,
#269000
1%
1,
b0 0
#270000
0%
0,
#271000
1%
1,
b0 0
#272000
0%
0,
#273000
1%
1,
b0 0
#274000
0%
0,
#275000
1%
1,
b0 0
#276000
0%
0,
#277000
1%
1,
b0 0
#278000
0%
0,
#279000
1%
1,
b0 0
#280000
0%
0,
#281000
1%
1,
b0 0
#282000
0%
0,
#283000
1%
1,
b0 0
#284000
0%
0,
#285000
1%
1,
b0 0
#286000
0%
0,
#287000
1%
1,
b0 0
#288000
0%
0,
#289000
1%
1,
b0 0
#290000
0%
0,
#291000
1%
1,
b0 0
#292000
0%
0,
#293000
1%
1,
b0 0
#294000
0%
0,
#295000
1%
1,
b0 0
#296000
0%
0,
#297000
1%
1,
b0 0
#298000
0%
0,
#299000
1%
1,
b0 0
#300000
0%
0,
#301000
1%
1,
b0 0
#302000
0%
0,
#303000
1%
1,
b0 0
#304000
0%
0,
#305000
1%
1,
b0 0
#306000
0%
0,
#307000
1%
1,
b0 0
#308000
0%
0,
#309000
1%
1,
b0 0
#310000
0%
0,
#311000
1%
1,
b0 0
#312000
0%
0,
#313000
1%
1,
b0 0
#314000
0%
0,
#315000
1%
1,
b0 0
#316000
0%
0,
#317000
1%
1,
b0 0
#318000
0%
0,
#319000
1%
1,
b0 0
#320000
0%
0,
#321000
1%
1,
b0 0
#322000
0%
0,
#323000
1%
1,
b0 0
#324000
0%
0,
#325000
1%
1,
b0 0
#326000
0%
0,
#327000
1%
1,
b0 0
#328000
0%
0,
#329000
1%
1,
b0 0
#330000
0%
0,
#331000
1%
1,
b0 0
#332000
0%
0,
#333000
1%
1,
b0 0
#334000
0%
0,
#335000
1%
1,
b0 0
#336000
0%
0,
#337000
1%
1,
b0 0
#338000
0%
0,
#339000
1%
1,
b0 0
#340000
0%
0,
#341000
1%
1,
b0 0
#342000
0%
0,
#343000
1%
1,
b0 0
#344000
0%
0,
#345000
1%
1,
b0 0
#346000
0%
0,
#347000
1%
1,
b0 0
#348000
0%
0,
#349000
1%
1,
b0 0
#350000
0%
0,
#351000
1%
1,
b0 0
#352000
0%
0,
#353000
1%
1,
b0 0
#354000
0%
0,
#355000
1%
1,
b0 0
#356000
0%
0,
#357000
1%
1,
b0 0
#358000
0%
0,
#359000
1%
1,
b0 0
#360000
0%
0,
#361000
1%
1,
b0 0
#362000
0%
0,
#363000
1%
1,
b0 0
#364000
0%
0,
#365000
1%
1,
b0 0
#366000
0%
0,
#367000
1%
1,
b0 0
#368000
0%
0,
#369000
1%
1,
b0 0
#370000
0%
0,
#371000
1%
1,
b0 0
#372000
0%
0,
#373000
1%
1,
b0 0
#374000
0%
0,
#375000
1%
1,
b0 0
#376000
0%
0,
#377000
1%
1,
b0 0
#378000
0%
0,
#379000
1%
1,
b0 0
#380000
0%
0,
#381000
1%
1,
b0 0
#382000
0%
0,
#383000
1%
1,
b0 0
#384000
0%
0,
#385000
1%
1,
b0 0
#386000
0%
0,
#387000
1%
1,
b0 0
#388000
0%
0,
#389000
1%
1,
b0 0
#390000
0%
0,
#391000
1%
1,
b0 0
#392000
0%
0,
#393000
1%
1,
b0 0
#394000
0%
0,
#395000
1%
1,
b0 0
#396000
0%
0,
#397000
1%
1,
b0 0
#398000
0%
0,
#399000
1%
1,
b0 0
#400000
0%
0,
#401000
1%
1,
b0 0
#402000
0%
0,
#403000
1%
1,
b0 0
#404000
0%
0,
#405000
1%
1,
b0 0
#406000
0%
0,
#407000
1%
1,
b0 0
#408000
0%
0,
#409000
1%
1,
b0 0
#410000
0%
0,
#411000
1%
1,
b0 0
#412000
0%
0,
#413000
1%
1,
b0 0
#414000
0%
0,
#415000
1%
1,
b0 0
#416000
0%
0,
#417000
1%
1,
b0 0
#418000
0%
0,
#419000
1%
1,
b0 0
#420000
0%
0,
#421000
1%
1,
b0 0
#422000
0%
0,
#423000
1%
1,
b0 0
#424000
0%
0,
#425000
1%
1,
b0 0
#426000
0%
0,
#427000
1%
1,
b0 0
#428000
0%
0,
#429000
1%
1,
b0 0
#430000
0%
0,
#431000
1%
1,
b0 0
#432000
0%
0,
#433000
1%
1,
b0 0
#434000
0%
0,
#435000
1%
1,
b0 0
#436000
0%
0,
#437000
1%
1,
b0 0
#438000
0%
0,
#439000
1%
1,
b0 0
#440000
0%
0,
#441000
1%
1,
b0 0
#442000
0%
0,
#443000
1%
1,
b0 0
#444000
0%
0,
#445000
1%
1,
b0 0
#446000
0%
0,
#447000
1%
1,
b0 0
#448000
0%
0,
#449000
1%
1,
b0 0
#450000
0%
0,
#451000
1%
1,
b0 0
#452000
0%
0,
#453000
1%
1,
b0 0
#454000
0%
0,
#455000
1%
1,
b0 0
#456000
0%
0,
#457000
1%
1,
b0 0
#458000
0%
0,
#459000
1%
1,
b0 0
#460000
0%
0,
#461000
1%
1,
b0 0
#462000
0%
0,
#463000
1%
1,
b0 0
#464000
0%
0,
#465000
1%
1,
b0 0
#466000
0%
0,
#467000
1%
1,
b0 0
#468000
0%
0,
#469000
1%
1,
b0 0
#470000
0%
0,
#471000
1%
1,
b0 0
#472000
0%
0,
#473000
1%
1,
b0 0
#474000
0%
0,
#475000
1%
1,
b0 0
#476000
0%
0,
#477000
1%
1,
b0 0
#478000
0%
0,
#479000
1%
1,
b0 0
#480000
0%
0,
#481000
1%
1,
b0 0
#482000
0%
0,
#483000
1%
1,
b0 0
#484000
0%
0,
#485000
1%
1,
b0 0
#486000
0%
0,
#487000
1%
1,
b0 0
#488000
0%
0,
#489000
1%
1,
b0 0
#490000
0%
0,
#491000
1%
1,
b0 0
#492000
0%
0,
#493000
1%
1,
b0 0
#494000
0%
0,
#495000
1%
1,
b0 0
#496000
0%
0,
#497000
1%
1,
b0 0
#498000
0%
0,
#499000
1%
1,
b0 0
#500000
0%
0,
#501000
1%
1,
b0 0
#502000
0%
0,
#503000
1%
1,
b0 0
#504000
0%
0,
#505000
1%
1,
b0 0
#506000
0%
0,
#507000
1%
1,
b0 0
#508000
0%
0,
#509000
1%
1,
b0 0
#510000
0%
0,
#511000
1%
1,
b0 0
#512000
0%
0,
#513000
1%
1,
b0 0
#514000
0%
0,
#515000
1%
1,
b0 0
#516000
0%
0,
#517000
1%
1,
b0 0
#518000
0%
0,
#519000
1%
1,
b0 0
#520000
0%
0,
#521000
1%
1,
b0 0
#522000
0%
0,
#523000
1%
1,
b0 0
#524000
0%
0,
#525000
1%
1,
b0 0
#526000
0%
0,
#527000
1%
1,
b0 0
#528000
0%
0,
#529000
1%
1,
b0 0
#530000
0%
0,
#531000
1%
1,
b0 0
#532000
0%
0,
#533000
1%
1,
b0 0
#534000
0%
0,
#535000
1%
1,
b0 0
#536000
0%
0,
#537000
1%
1,
b0 0
#538000
0%
0,
#539000
1%
1,
b0 0
#540000
0%
0,
#541000
1%
1,
b0 0
#542000
0%
0,
#543000
1%
1,
b0 0
#544000
0%
0,
#545000
1%
1,
b0 0
#546000
0%
0,
#547000
1%
1,
b0 0
#548000
0%
0,
#549000
1%
1,
b0 0
#550000
0%
0,
#551000
1%
1,
b0 0
#552000
0%
0,
#553000
1%
1,
b0 0
#554000
0%
0,
#555000
1%
1,
b0 0
#556000
0%
0,
#557000
1%
1,
b0 0
#558000
0%
0,
#559000
1%
1,
b0 0
#560000
0%
0,
#561000
1%
1,
b0 0
#562000
0%
0,
#563000
1%
1,
b0 0
#564000
0%
0,
#565000
1%
1,
b0 0
#566000
0%
0,
#567000
1%
1,
b0 0
#568000
0%
0,
#569000
1%
1,
b0 0
#570000
0%
0,
#571000
1%
1,
b0 0
#572000
0%
0,
#573000
1%
1,
b0 0
#574000
0%
0,
#575000
1%
1,
b0 0
#576000
0%
0,
#577000
1%
1,
b0 0
#578000
0%
0,
#579000
1%
1,
b0 0
#580000
0%
0,
#581000
1%
1,
b0 0
#582000
0%
0,
#583000
1%
1,
b0 0
#584000
0%
0,
#585000
1%
1,
b0 0
#586000
0%
0,
#587000
1%
1,
b0 0
#588000
0%
0,
#589000
1%
1,
b0 0
#590000
0%
0,
#591000
1%
1,
b0 0
#592000
0%
0,
#593000
1%
1,
b0 0
#594000
0%
0,
#595000
1%
1,
b0 0
#596000
0%
0,
#597000
1%
1,
b0 0
#598000
0%
0,
#599000
1%
1,
b0 0
#600000
0%
0,
#601000
1%
1,
b0 0
#602000
0%
0,
#603000
1%
1,
b0 0
#604000
0%
0,
#605000
1%
1,
b0 0
#606000
0%
0,
#607000
1%
1,
b0 0
#608000
0%
0,
#609000
1%
1,
b0 0
#610000
0%
0,
#611000
1%
1,
b0 0
#612000
0%
0,
#613000
1%
1,
b0 0
#614000
0%
0,
#615000
1%
1,
b0 0
#616000
0%
0,
#617000
1%
1,
b0 0
#618000
0%
0,
#619000
1%
1,
b0 0
#620000
0%
0,
#621000
1%
1,
b0 0
#622000
0%
0,
#623000
1%
1,
b0 0
#624000
0%
0,
#625000
1%
1,
b0 0
#626000
0%
0,
#627000
1%
1,
b0 0
#628000
0%
0,
#629000
1%
1,
b0 0
#630000
0%
0,
#631000
1%
1,
b0 0
#632000
0%
0,
#633000
1%
1,
b0 0
#634000
0%
0,
#635000
1%
1,
b0 0
#636000
0%
0,
#637000
1%
1,
b0 0
#638000
0%
0,
#639000
1%
1,
b0 0
#640000
0%
0,
#641000
1%
1,
b0 0
#642000
0%
0,
#643000
1%
1,
b0 0
#644000
0%
0,
#645000
1%
1,
b0 0
#646000
0%
0,
#647000
1%
1,
b0 0
#648000
0%
0,
#649000
1%
1,
b0 0
#650000
0%
0,
#651000
1%
1,
b0 0
#652000
0%
0,
#653000
1%
1,
b0 0
#654000
0%
0,
#655000
1%
1,
b0 0
#656000
0%
0,
#657000
1%
1,
b0 0
#658000
0%
0,
#659000
1%
1,
b0 0
#660000
0%
0,
#661000
1%
1,
b0 0
#662000
0%
0,
#663000
1%
1,
b0 0
#664000
0%
0,
#665000
1%
1,
b0 0
#666000
0%
0,
#667000
1%
1,
b0 0
#668000
0%
0,
#669000
1%
1,
b0 0
#670000
0%
0,
#671000
1%
1,
b0 0
#672000
0%
0,
#673000
1%
1,
b0 0
#674000
0%
0,
#675000
1%
1,
b0 0
#676000
0%
0,
#677000
1%
1,
b0 0
#678000
0%
0,
#679000
1%
1,
b0 0
#680000
0%
0,
#681000
1%
1,
b0 0
#682000
0%
0,
#683000
1%
1,
b0 0
#684000
0%
0,
#685000
1%
1,
b0 0
#686000
0%
0,
#687000
1%
1,
b0 0
#688000
0%
0,
#689000
1%
1,
b0 0
#690000
0%
0,
#691000
1%
1,
b0 0
#692000
0%
0,
#693000
1%
1,
b0 0
#694000
0%
0,
#695000
1%
1,
b0 0
#696000
0%
0,
#697000
1%
1,
b0 0
#698000
0%
0,
#699000
1%
1,
b0 0
#700000
0%
0,
#701000
1%
1,
b0 0
#702000
0%
0,
#703000
1%
1,
b0 0
#704000
0%
0,
#705000
1%
1,
b0 0
#706000
0%
0,
#707000
1%
1,
b0 0
#708000
0%
0,
#709000
1%
1,
b0 0
#710000
0%
0,
#711000
1%
1,
b0 0
#712000
0%
0,
#713000
1%
1,
b0 0
#714000
0%
0,
#715000
1%
1,
b0 0
#716000
0%
0,
#717000
1%
1,
b0 0
#718000
0%
0,
#719000
1%
1,
b0 0
#720000
0%
0,
#721000
1%
1,
b0 0
#722000
0%
0,
#723000
1%
1,
b0 0
#724000
0%
0,
#725000
1%
1,
b0 0
#726000
0%
0,
#727000
1%
1,
b0 0
#728000
0%
0,
#729000
1%
1,
b0 0
#730000
0%
0,
#731000
1%
1,
b0 0
#732000
0%
0,
#733000
1%
1,
b0 0
#734000
0%
0,
#735000
1%
1,
b0 0
#736000
0%
0,
#737000
1%
1,
b0 0
#738000
0%
0,
#739000
1%
1,
b0 0
#740000
0%
0,
#741000
1%
1,
b0 0
#742000
0%
0,
#743000
1%
1,
b0 0
#744000
0%
0,
#745000
1%
1,
b0 0
#746000
0%
0,
#747000
1%
1,
b0 0
#748000
0%
0,
#749000
1%
1,
b0 0
#750000
0%
0,
#751000
1%
1,
b0 0
#752000
0%
0,
#753000
1%
1,
b0 0
#754000
0%
0,
#755000
1%
1,
b0 0
#756000
0%
0,
#757000
1%
1,
b0 0
#758000
0%
0,
#759000
1%
1,
b0 0
#760000
0%
0,
#761000
1%
1,
b0 0
#762000
0%
0,
#763000
1%
1,
b0 0
#764000
0%
0,
#765000
1%
1,
b0 0
#766000
0%
0,
#767000
1%
1,
b0 0
#768000
0%
0,
#769000
1%
1,
b0 0
#770000
0%
0,
#771000
1%
1,
b0 0
#772000
0%
0,
#773000
1%
1,
b0 0
#774000
0%
0,
#775000
1%
1,
b0 0
#776000
0%
0,
#777000
1%
1,
b0 0
#778000
0%
0,
#779000
1%
1,
b0 0
#780000
0%
0,
#781000
1%
1,
b0 0
#782000
0%
0,
#783000
1%
1,
b0 0
#784000
0%
0,
#785000
1%
1,
b0 0
#786000
0%
0,
#787000
1%
1,
b0 0
#788000
0%
0,
#789000
1%
1,
b0 0
#790000
0%
0,
#791000
1%
1,
b0 0
#792000
0%
0,
#793000
1%
1,
b0 0
#794000
0%
0,
#795000
1%
1,
b0 0
#796000
0%
0,
#797000
1%
1,
b0 0
#798000
0%
0,
#799000
1%
1,
b0 0
#800000
0%
0,
#801000
1%
1,
b0 0
#802000
0%
0,
#803000
1%
1,
b0 0
#804000
0%
0,
#805000
1%
1,
b0 0
#806000
0%
0,
#807000
1%
1,
b0 0
#808000
0%
0,
#809000
1%
1,
b0 0
#810000
0%
0,
#811000
1%
1,
b0 0
#812000
0%
0,
#813000
1%
1,
b0 0
#814000
0%
0,
#815000
1%
1,
b0 0
#816000
0%
0,
#817000
1%
1,
b0 0
#818000
0%
0,
#819000
1%
1,
b0 0
#820000
0%
0,
#821000
1%
1,
b0 0
#822000
0%
0,
#823000
1%
1,
b0 0
#824000
0%
0,
#825000
1%
1,
b0 0
#826000
0%
0,
#827000
1%
1,
b0 0
#828000
0%
0,
#829000
1%
1,
b0 0
#830000
0%
0,
#831000
1%
1,
b0 0
#832000
0%
0,
#833000
1%
1,
b0 0
#834000
0%
0,
#835000
1%
1,
b0 0
#836000
0%
0,
#837000
1%
1,
b0 0
#838000
0%
0,
#839000
1%
1,
b0 0
#840000
0%
0,
#841000
1%
1,
b0 0
#842000
0%
0,
#843000
1%
1,
b0 0
#844000
0%
0,
#845000
1%
1,
b0 0
#846000
0%
0,
#847000
1%
1,
b0 0
#848000
0%
0,
#849000
1%
1,
b0 0
#850000
0%
0,
#851000
1%
1,
b0 0
#852000
0%
0,
#853000
1%
1,
b0 0
#854000
0%
0,
#855000
1%
1,
b0 0
#856000
0%
0,
#857000
1%
1,
b0 0
#858000
0%
0,
#859000
1%
1,
b0 0
#860000
0%
0,
#861000
1%
1,
b0 0
#862000
0%
0,
#863000
1%
1,
b0 0
#864000
0%
0,
#865000
1%
1,
b0 0
#866000
0%
0,
#867000
1%
1,
b0 0
#868000
0%
0,
#869000
1%
1,
b0 0
#870000
0%
0,
#871000
1%
1,
b0 0
#872000
0%
0,
#873000
1%
1,
b0 0
#874000
0%
0,
#875000
1%
1,
b0 0
#876000
0%
0,
#877000
1%
1,
b0 0
#878000
0%
0,
#879000
1%
1,
b0 0
#880000
0%
0,
#881000
1%
1,
b0 0
#882000
0%
0,
#883000
1%
1,
b0 0
#884000
0%
0,
#885000
1%
1,
b0 0
#886000
0%
0,
#887000
1%
1,
b0 0
#888000
0%
0,
#889000
1%
1,
b0 0
#890000
0%
0,
#891000
1%
1,
b0 0
#892000
0%
0,
#893000
1%
1,
b0 0
#894000
0%
0,
#895000
1%
1,
b0 0
#896000
0%
0,
#897000
1%
1,
b0 0
#898000
0%
0,
#899000
1%
1,
b0 0
#900000
0%
0,
#901000
1%
1,
b0 0
#902000
0%
0,
#903000
1%
1,
b0 0
#904000
0%
0,
#905000
1%
1,
b0 0
#906000
0%
0,
#907000
1%
1,
b0 0
#908000
0%
0,
#909000
1%
1,
b0 0
#910000
0%
0,
#911000
1%
1,
b0 0
#912000
0%
0,
#913000
1%
1,
b0 0
#914000
0%
0,
#915000
1%
1,
b0 0
#916000
0%
0,
#917000
1%
1,
b0 0
#918000
0%
0,
#919000
1%
1,
b0 0
#920000
0%
0,
#921000
1%
1,
b0 0
#922000
0%
0,
#923000
1%
1,
b0 0
#924000
0%
0,
#925000
1%
1,
b0 0
#926000
0%
0,
#927000
1%
1,
b0 0
#928000
0%
0,
#929000
1%
1,
b0 0
#930000
0%
0,
#931000
1%
1,
b0 0
#932000
0%
0,
#933000
1%
1,
b0 0
#934000
0%
0,
#935000
1%
1,
b0 0
#936000
0%
0,
#937000
1%
1,
b0 0
#938000
0%
0,
#939000
1%
1,
b0 0
#940000
0%
0,
#941000
1%
1,
b0 0
#942000
0%
0,
#943000
1%
1,
b0 0
#944000
0%
0,
#945000
1%
1,
b0 0
#946000
0%
0,
#947000
1%
1,
b0 0
#948000
0%
0,
#949000
1%
1,
b0 0
#950000
0%
0,
#951000
1%
1,
b0 0
#952000
0%
0,
#953000
1%
1,
b0 0
#954000
0%
0,
#955000
1%
1,
b0 0
#956000
0%
0,
#957000
1%
1,
b0 0
#958000
0%
0,
#959000
1%
1,
b0 0
#960000
0%
0,
#961000
1%
1,
b0 0
#962000
0%
0,
#963000
1%
1,
b0 0
#964000
0%
0,
#965000
1%
1,
b0 0
#966000
0%
0,
#967000
1%
1,
b0 0
#968000
0%
0,
#969000
1%
1,
b0 0
#970000
0%
0,
#971000
1%
1,
b0 0
#972000
0%
0,
#973000
1%
1,
b0 0
#974000
0%
0,
#975000
1%
1,
b0 0
#976000
0%
0,
#977000
1%
1,
b0 0
#978000
0%
0,
#979000
1%
1,
b0 0
#980000
0%
0,
#981000
1%
1,
b0 0
#982000
0%
0,
#983000
1%
1,
b0 0
#984000
0%
0,
#985000
1%
1,
b0 0
#986000
0%
0,
#987000
1%
1,
b0 0
#988000
0%
0,
#989000
1%
1,
b0 0
#990000
0%
0,
#991000
1%
1,
b0 0
#992000
0%
0,
#993000
1%
1,
b0 0
#994000
0%
0,
#995000
1%
1,
b0 0
#996000
0%
0,
#997000
1%
1,
b0 0
#998000
0%
0,
#999000
1%
1,
b0 0
